SD/SD.v
// Sequence Detector (0110 and overlapping occurrences of the pattern)

module SD(x,clk,reset,z);

    input x,clk,reset;
    output reg z;
    parameter S0 = 0, S1 = 1, S2 = 2, S3 = 3;
    reg [1:0]PS, NS;

    always @(posedge clk or posedge reset) 
        if(reset) PS <=S0;
        else PS <= NS;
    
    always @(PS,x)
        case(PS)
        S0: begin
                z=x?0:0;
                NS=x?S0:S1;
            end

        S1: begin
                z=x?0:0;
                NS=x?S2:S1;
            end

        S2: begin
                z=x?0:0;
                NS=x?S3:S1;
            end

        S3: begin
                z=x?0:1;
                NS=x?S0:S1;
            end
        endcase
endmodule

SD/SDtest.v
module SDtest;

    reg x,clk,reset;
    SD sequenceDetector (x,clk,reset,z);

    initial 
        begin
            $dumpfile("SD.vcd");
            $dumpvars(0,SDtest); 
            #15 reset = 1'b0;           
        end

    always #5 clk = ~clk;

    initial
        begin
            #12 x=0;
            #10 x=0;
            #10 x=1;
            #10 x=1;
            #10 x=0;
            #10 x=1;
            #10 x=1;
            #10 x=0;
            #10 x=0;
            #10 x=1;
            #10 x=1;
            #10 x=0;
            #10 $finish;
        end

endmodule

SD/SD.vcd
$date
	Mon Jul 24 09:14:58 2023
$end
$version
	Icarus Verilog
$end
$timescale
	1s
$end
$scope module SDtest $end
$var wire 1 ! z $end
$var reg 1 " clk $end
$var reg 1 # reset $end
$var reg 1 $ x $end
$scope module sequenceDetector $end
$var wire 1 " clk $end
$var wire 1 # reset $end
$var wire 1 $ x $end
$var parameter 32 % S0 $end
$var parameter 32 & S1 $end
$var parameter 32 ' S2 $end
$var parameter 32 ( S3 $end
$var reg 2 ) NS [1:0] $end
$var reg 2 * PS [1:0] $end
$var reg 1 ! z $end
$upscope $end
$upscope $end
$enddefinitions $end
$comment Show the parameter values. $end
$dumpall
b11 (
b10 '
b1 &
b0 %
$end
#0
$dumpvars
bx *
bx )
x$
x#
x"
x!
$end
#12
0$
#15
0#
#32
1$
#52
0$
#62
1$
#82
0$
#102
1$
#122
0$
