FSM/FSM.v
module cyclic_lamp (clock,light);
    
    input clock;
    output reg [2:0]light;
    
    parameter S0 = 0, S1 = 1, S2 = 2;
    parameter RED = 3'b100, GREEN = 3'b010, YELLOW = 3'b001;

    reg [0:1]state;

    always @(posedge clock)
        case (state)
            S0: begin
                    light <= GREEN; state <= S1;
                end

            S1: begin
                    light <= YELLOW; state <= S2;
                end

            S2: begin
                    light <= RED; state <= S0;
                end

            default: begin
                        light <= RED; state <= S0;   
                     end
        endcase
endmodule

/* Alternative way to generate less flip flops.

Separate the always block into two always blocks.
Trigger by 'state'.

    always @(posedge clock)
        case (state)
            S0: state <= S1;
            S1: state <= S2;
            S2: state <= S0;
            default: state <= S0;
        endcase

    always @(state)
        case (state)
            S0: light = RED;
            S1: light = GREEN;
            S2: light = YELLOW;
            default: light = RED;
        endcase
*/

FSM/FSMtest.v
module cyclic_lamp_test;
    
    reg clk;
    wire [2:0]light;
    
    cyclic_lamp LAMP(clk,light);

    always #5 clk = ~clk;

    initial 
        begin
            clk = 1'b0;
            #100 $finish;
        end
   
    initial
        begin
            $dumpfile("cyclic_lamp.vcd");
            $dumpvars(0,cyclic_lamp_test);
            $monitor($time, "RGY:%b",light);
        end
endmodule

FSM/cyclic_lamp.vcd
$date
	Sun Jul 23 08:51:03 2023
$end
$version
	Icarus Verilog
$end
$timescale
	1s
$end
$scope module cyclic_lamp_test $end
$var wire 3 ! light [2:0] $end
$var reg 1 " clk $end
$scope module LAMP $end
$var wire 1 " clock $end
$var parameter 3 # GREEN $end
$var parameter 3 $ RED $end
$var parameter 32 % S0 $end
$var parameter 32 & S1 $end
$var parameter 32 ' S2 $end
$var parameter 3 ( YELLOW $end
$var reg 3 ) light [2:0] $end
$var reg 2 * state [0:1] $end
$upscope $end
$upscope $end
$enddefinitions $end
$comment Show the parameter values. $end
$dumpall
b1 (
b10 '
b1 &
b0 %
b100 $
b10 #
$end
#0
$dumpvars
bx *
bx )
0"
bx !
$end
#5
b0 *
b100 !
b100 )
1"
#10
0"
#15
b1 *
b10 !
b10 )
1"
#20
0"
#25
b10 *
b1 !
b1 )
1"
#30
0"
#35
b0 *
b100 !
b100 )
1"
#40
0"
#45
b1 *
b10 !
b10 )
1"
#50
0"
#55
b10 *
b1 !
b1 )
1"
#60
0"
#65
b0 *
b100 !
b100 )
1"
#70
0"
#75
b1 *
b10 !
b10 )
1"
#80
0"
#85
b10 *
b1 !
b1 )
1"
#90
0"
#95
b0 *
b100 !
b100 )
1"
